[
    {
        "semesterId": "213",
        "semesterName": "Fall",
        "semesterYear": 2021,
        "studentId": "212-35-731",
        "courseId": "C117",
        "customCourseId": "MAT 101",
        "courseTitle": "Mathematics I",
        "totalCredit": 3.0,
        "grandTotal": null,
        "pointEquivalent": 2.75,
        "gradeLetter": "B-",
        "cgpa": 1.92,
        "blocked": "N",
        "blockCause": null,
        "tevalSubmitted": "SUBMITTED",
        "teval": "Y",
        "semesterAccountsClearance": null
    },
    {
        "semesterId": "213",
        "semesterName": "Fall",
        "semesterYear": 2021,
        "studentId": "212-35-731",
        "courseId": "C163",
        "customCourseId": "SE 121",
        "courseTitle": "Structured Programming",
        "totalCredit": 3.0,
        "grandTotal": null,
        "pointEquivalent": 2.25,
        "gradeLetter": "C",
        "cgpa": 1.92,
        "blocked": "N",
        "blockCause": null,
        "tevalSubmitted": "SUBMITTED",
        "teval": "Y",
        "semesterAccountsClearance": null
    },
    {
        "semesterId": "213",
        "semesterName": "Fall",
        "semesterYear": 2021,
        "studentId": "212-35-731",
        "courseId": "D548",
        "customCourseId": "SE 122",
        "courseTitle": "Structured Programming Lab",
        "totalCredit": 1.0,
        "grandTotal": null,
        "pointEquivalent": 3.25,
        "gradeLetter": "B+",
        "cgpa": 1.92,
        "blocked": "N",
        "blockCause": null,
        "tevalSubmitted": "SUBMITTED",
        "teval": "Y",
        "semesterAccountsClearance": null
    },
    {
        "semesterId": "213",
        "semesterName": "Fall",
        "semesterYear": 2021,
        "studentId": "212-35-731",
        "courseId": "T325",
        "customCourseId": "PHY 101",
        "courseTitle": "Physics I",
        "totalCredit": 3.0,
        "grandTotal": null,
        "pointEquivalent": 0.0,
        "gradeLetter": "F",
        "cgpa": 1.92,
        "blocked": "N",
        "blockCause": null,
        "tevalSubmitted": "SUBMITTED",
        "teval": "Y",
        "semesterAccountsClearance": null
    },
    {
        "semesterId": "213",
        "semesterName": "Fall",
        "semesterYear": 2021,
        "studentId": "212-35-731",
        "courseId": "T504",
        "customCourseId": "SE 123",
        "courseTitle": "Discrete Mathematics",
        "totalCredit": 3.0,
        "grandTotal": null,
        "pointEquivalent": 2.25,
        "gradeLetter": "C",
        "cgpa": 1.92,
        "blocked": "N",
        "blockCause": null,
        "tevalSubmitted": "SUBMITTED",
        "teval": "Y",
        "semesterAccountsClearance": null
    }
]