[
    {
        "semesterId": "233",
        "semesterName": "Fall",
        "semesterYear": 2023,
        "studentId": "212-35-738",
        "courseId": "T687",
        "customCourseId": "SE 224",
        "courseTitle": "Database System Lab",
        "totalCredit": 1.0,
        "grandTotal": null,
        "pointEquivalent": 3.25,
        "gradeLetter": "B+",
        "cgpa": 0.41,
        "blocked": "N",
        "blockCause": null,
        "tevalSubmitted": "SUBMITTED",
        "teval": "Y",
        "semesterAccountsClearance": "accounts-clearance-pending"
    },
    {
        "semesterId": "233",
        "semesterName": "Fall",
        "semesterYear": 2023,
        "studentId": "212-35-738",
        "courseId": "T589",
        "customCourseId": "SE 214",
        "courseTitle": "Algorithms Design & Analysis",
        "totalCredit": 3.0,
        "grandTotal": null,
        "pointEquivalent": 0.0,
        "gradeLetter": "I",
        "cgpa": 0.41,
        "blocked": "N",
        "blockCause": null,
        "tevalSubmitted": "SUBMITTED",
        "teval": "Y",
        "semesterAccountsClearance": "accounts-clearance-pending"
    },
    {
        "semesterId": "233",
        "semesterName": "Fall",
        "semesterYear": 2023,
        "studentId": "212-35-738",
        "courseId": "T587",
        "customCourseId": "SE 211",
        "courseTitle": "Object Oriented Concepts",
        "totalCredit": 3.0,
        "grandTotal": null,
        "pointEquivalent": 0.0,
        "gradeLetter": "F",
        "cgpa": 0.41,
        "blocked": "N",
        "blockCause": null,
        "tevalSubmitted": "SUBMITTED",
        "teval": "Y",
        "semesterAccountsClearance": "accounts-clearance-pending"
    },
    {
        "semesterId": "233",
        "semesterName": "Fall",
        "semesterYear": 2023,
        "studentId": "212-35-738",
        "courseId": "T590",
        "customCourseId": "SE 215",
        "courseTitle": "Algorithms Design & Analysis Lab",
        "totalCredit": 1.0,
        "grandTotal": null,
        "pointEquivalent": 0.0,
        "gradeLetter": "I",
        "cgpa": 0.41,
        "blocked": "N",
        "blockCause": null,
        "tevalSubmitted": "SUBMITTED",
        "teval": "Y",
        "semesterAccountsClearance": "accounts-clearance-pending"
    }
]